src/Alu.v
module Alu #(
    parameter DATA_WIDTH = 8
) (
    //inputs
    input i_clk,
    input i_rst,
    input i_opcode,
    input i_bus_writable,
    input [DATA_WIDTH-1:0] i_a,
    input [DATA_WIDTH-1:0] i_b,
    //outputs
    output reg o_jc,
    output reg o_jz,
    output wire [DATA_WIDTH-1:0] o_c
);

    reg carry;
    reg [DATA_WIDTH-1:0] tmp;

    always @ (posedge i_clk or posedge i_rst) begin
        if (i_rst) begin
            o_jc <= 1'b0;
            o_jz <= 1'b0;
        end
        else if (i_bus_writable) begin
            o_jc <= carry;
            if (tmp == 0 && !i_opcode)
            o_jz <= 1'b1;
            else
            o_jz <= 1'b0;
        end
    end

    always@(*) begin
        if (i_opcode) begin
            {carry,tmp} = i_a + i_b;
        end
        else begin
            {carry,tmp} = i_a - i_b;
        end
    end

    assign o_c = i_bus_writable ? tmp : {DATA_WIDTH{1'bz}};

endmodule

tb/Alu_tb.v
`default_nettype none
`timescale 1ns/1ns

`define assert(signal, value)\
    if (signal !== value) begin\
    $display("Assertion Failed at %2d in %m: signal != value", $time);\
    $finish;\
    end

module Alu_tb;
    localparam DATA_WIDTH = 8;

    //variables to connect to dut ports
    reg clk;
    reg rst;
    reg opcode;
    reg bus_writable;
    reg [DATA_WIDTH-1:0]a;
    reg [DATA_WIDTH-1:0]b;


    Alu #(.DATA_WIDTH(DATA_WIDTH)) dut (
        .i_clk(clk),
        .i_rst(rst),
        .i_opcode(opcode),
        .i_bus_writable(bus_writable),
        .i_a(a),
        .i_b(b)
    );


    initial begin
        //initialize signals
        clk = 0;
        rst = 1;
        bus_writable = 0;
        opcode = 1'b1;
        a = 8'b00000000;
        b = 8'b11111111;

    @(posedge clk); //check reset 
    #1
    `assert(dut.o_jc, 1'b0);
    `assert(dut.o_jz, 1'b0);

    @(negedge clk); //let alu drive bus and release rst
    rst = 0;
    bus_writable = 1'b1;

    @(posedge clk);
    #1
    `assert(dut.o_c, 8'b11111111);
    `assert(dut.o_jc, 1'b0);
    `assert(dut.o_jz, 1'b0);

    @(negedge clk);
    a = 8'b11111111;
    b = 8'b00000001;

    @(posedge clk); // check addition with carry
    #1
    `assert(dut.tmp, 8'b00000000);
    `assert(dut.carry, 1'b1);
    `assert(dut.o_jc, 1'b1);
    `assert(dut.o_jz, 1'b0);

    @(negedge clk); //set to subtract
    opcode = 1'b0;
    a = 8'b11110000;
    b = 8'b11110000;

    @(posedge clk); //check subtraction with zero flag
    #1
    `assert(dut.tmp, 8'b0);
    `assert(dut.carry, 1'b0);
    `assert(dut.o_jz, 1'b1);
    `assert(dut.o_jc, 1'b0);

    @(negedge clk); //set to subtract with carry needed
    a = 8'b00000001;
    b = 8'b00000010;

    @(posedge clk); //check subtraction with carry needed
    #1
    `assert(dut.tmp, 8'b11111111);
    `assert(dut.carry, 1'b1);
    `assert(dut.o_c, 8'b11111111);
    `assert(dut.o_jc, 1'b1);
    `assert(dut.o_jz, 1'b0);

    @(negedge clk); //check theat when we = 0, o_c = z
    bus_writable = 1'b0;

    @(posedge clk); 
    #1
    `assert(dut.o_c, {DATA_WIDTH{1'bz}});

    #5
    $display("TestBench Passed!");
    $finish;
    end

    always #5 clk = ~clk;

    always @(posedge clk) begin 
       $display("Clock toggled at time %2t, clk = %0b, bus_writable = %0b, opcode = %0b, a = %0b, b = %0b", $time, clk, bus_writable,opcode,a,b); 
        end  

    initial begin 
        $dumpfile("Alu.vcd"); 
        $dumpvars;  
        end 

endmodule

Alu.vcd
$date
	Sat Nov 29 22:03:08 2025
$end
$version
	Icarus Verilog
$end
$timescale
	1ns
$end
$scope module Alu_tb $end
$var parameter 32 ! DATA_WIDTH $end
$var reg 8 " a [7:0] $end
$var reg 8 # b [7:0] $end
$var reg 1 $ bus_writable $end
$var reg 1 % clk $end
$var reg 1 & opcode $end
$var reg 1 ' rst $end
$scope module dut $end
$var wire 8 ( i_a [7:0] $end
$var wire 8 ) i_b [7:0] $end
$var wire 1 $ i_bus_writable $end
$var wire 1 % i_clk $end
$var wire 1 & i_opcode $end
$var wire 1 ' i_rst $end
$var wire 8 * o_c [7:0] $end
$var parameter 32 + DATA_WIDTH $end
$var reg 1 , carry $end
$var reg 1 - o_jc $end
$var reg 1 . o_jz $end
$var reg 8 / tmp [7:0] $end
$upscope $end
$upscope $end
$enddefinitions $end
$comment Show the parameter values. $end
$dumpall
b1000 +
b1000 !
$end
#0
$dumpvars
b11111111 /
0.
0-
0,
bz *
b11111111 )
b0 (
1'
1&
0%
0$
b11111111 #
b0 "
$end
#5
1%
#10
b11111111 *
1$
0'
0%
#15
1%
#20
b0 *
1,
b0 /
b1 #
b1 )
b11111111 "
b11111111 (
0%
#25
1-
1%
#30
0,
b11110000 #
b11110000 )
b11110000 "
b11110000 (
0&
0%
#35
1.
0-
1%
#40
b11111111 *
1,
b11111111 /
b10 #
b10 )
b1 "
b1 (
0%
#45
0.
1-
1%
#50
bz *
0$
0%
