src/Controller.v
module Controller #(
    parameter DATA_WIDTH = 8
) (
    //inputs
    input i_clk,
    input i_rst,
    input [DATA_WIDTH-1:0] i_inst,
    input i_jc,
    input i_jz,
    //output
    output reg [7:0] o_write_enable_bus,
    output reg o_opcode,
    output reg o_we_mem,
    output reg o_load_pc,
    output reg o_load_tmp,
    output reg o_load_mar,
    output reg o_load_inst,
    output reg o_load_acc,
    output reg o_jmp,
    output reg o_imme
);
    // DEFINE INSTRUCTION SET (top 4 pits of i_inst[7:4])
    localparam OP_ADD   = 4'b0000;
    localparam OP_SUB   = 4'b0001;
    localparam OP_LOAD  = 4'b0010;
    localparam OP_STORE = 4'b0011;
    localparam OP_IMME  = 4'b0100;
    localparam OP_JMP   = 4'b0101;
    localparam OP_JC    = 4'b0110;
    localparam OP_JZ    = 4'b0111;

    //STATES
    localparam PC_OUT       = 3'b000;
    localparam LOAD_IR      = 3'b001;
    localparam DECODE       = 3'b010;
    localparam EXECUTE      = 3'b011;
    localparam LOAD_TMP     = 3'b100;
    localparam LOAD_ACC     = 3'b101;
    localparam STORE_MEM    = 3'b110;
    localparam INCREMENT_PC = 3'b111;

    //write_enable_bus
    localparam PC           = 8'b0000_0001;
    localparam INCREMENTER  = 8'b0000_0010;
    localparam MEM          = 8'b0000_0100;
    localparam ALU          = 8'b0000_1000;
    localparam ACC          = 8'b0001_0000;
    localparam TMP          = 8'b0010_0000;
    localparam DECODER      = 8'b0100_0000;

    reg [2:0] state = PC_OUT;
    reg [2:0] next_state = PC_OUT;
    reg opcode;

    //on clock cycle or reset
    always @ (posedge i_clk or posedge i_rst) begin
        if (i_rst) begin 
            state <= PC_OUT;
            opcode <= 1'b0;
        end
        else begin
            state <= next_state;
            if (state == DECODE) begin
                if(i_inst[7:4] == OP_ADD) begin
                    opcode <= 1'b1;
                end
                else begin
                    opcode <= 1'b0; 
                end                   
            end
        end 
    end

    //FSM
    always @(*) begin
        next_state = state;                              
        o_load_pc   = 1'b0;
        o_load_mar  = 1'b0;
        o_opcode    = 1'b0;
        o_we_mem    = 1'b0;
        o_load_acc  = 1'b0;
        o_load_tmp  = 1'b0;
        o_jmp       = 1'b0;
        o_imme      = 1'b0;
        o_load_inst = 1'b0;
        case (state)
        PC_OUT: begin
            o_write_enable_bus = PC;
            o_load_mar = 1'b1;
            next_state = LOAD_IR;
        end
        LOAD_IR : begin
            o_write_enable_bus = MEM;
            o_load_inst = 1'b1;
            next_state = DECODE;
        end
        DECODE: begin
            o_write_enable_bus = MEM;
            case (i_inst[7:4])
            OP_ADD,OP_SUB: begin
                o_load_mar = 1'b1;
                next_state = LOAD_TMP;
            end
            OP_LOAD: begin
                o_load_mar = 1'b1;
                next_state = LOAD_ACC;
            end
            OP_STORE: begin
                o_load_mar = 1'b1;
                next_state = STORE_MEM;
            end
            OP_IMME: begin
                o_imme = 1'b1;
                o_load_acc = 1'b1;
                next_state = INCREMENT_PC;
            end
            OP_JMP: begin
                o_jmp = 1'b1;
                o_load_pc = 1'b1;
                next_state = PC_OUT;
            end
            OP_JC: begin
                if (i_jc) begin
                    o_jmp = 1'b1;
                    o_load_pc = 1'b1;
                    next_state = PC_OUT; 
                end
                else begin
                    next_state = INCREMENT_PC;
                    end
            end
            OP_JZ: begin
                if (i_jz) begin
                    o_jmp = 1'b1;
                    o_load_pc = 1'b1;
                    next_state = PC_OUT; 
                end
                else begin
                    next_state = INCREMENT_PC;
                    end
            end
            default : begin
                $display ("Should not end here!");
            end
            endcase
        end
        LOAD_TMP: begin
            o_write_enable_bus = MEM;
            o_load_tmp = 1'b1;
            next_state = EXECUTE;
        end
        EXECUTE: begin
            o_opcode = opcode;
            o_write_enable_bus = ALU;
            o_load_acc = 1'b1;
            next_state = INCREMENT_PC;
        end
        LOAD_ACC: begin
            o_write_enable_bus = MEM;
            o_load_acc = 1'b1;
            next_state = INCREMENT_PC;
        end
        STORE_MEM: begin
            o_write_enable_bus = ACC;
            o_we_mem = 1'b1;
            next_state = INCREMENT_PC; 
        end 
        INCREMENT_PC: begin
            o_write_enable_bus = INCREMENTER;
            o_load_pc = 1'b1;
            next_state = PC_OUT;
        end
        endcase
    end
endmodule

tb/Controller_tb.v
`default_nettype none
`timescale 1ns/1ns

`define assert(signal, value) \
    if (signal !== value) begin \
        $display("Assertion Failed at %2d in %m: Signal != value", $time); \
        $finish; \
    end 

module controller_tb;

    localparam DATA_WIDTH = 8;

    reg clk;
    reg rst;
    reg [DATA_WIDTH-1:0] inst;
    reg jc;
    reg jz;

    wire [7:0] write_enable_bus;
    wire opcode;
    wire we_mem;
    wire load_pc;
    wire load_tmp;
    wire load_mar;
    wire load_inst;
    wire load_acc;
    wire jmp;
    wire imme;

    //Write enable bus access
    localparam PC           = 8'b0000_0001;
    localparam INCREMENTER  = 8'b0000_0010;
    localparam MEM          = 8'b0000_0100;
    localparam ALU          = 8'b0000_1000;
    localparam ACC          = 8'b0001_0000;
    localparam TMP          = 8'b0010_0000;
    localparam DECODER      = 8'b0100_0000;

    //Decoding Operations
    localparam OP_ADD   = 4'b0000;
    localparam OP_SUB   = 4'b0001;
    localparam OP_LOAD  = 4'b0010;
    localparam OP_STORE = 4'b0011;
    localparam OP_IMME  = 4'b0100;
    localparam OP_JMP   = 4'b0101;
    localparam OP_JC    = 4'b0110;
    localparam OP_JZ    = 4'b0111;

    Controller #(.DATA_WIDTH(DATA_WIDTH)) dut (
        //inputs
        .i_clk(clk),
        .i_rst(rst),
        .i_inst(inst),
        .i_jc(jc),
        .i_jz(jz),
        //outputs
        .o_write_enable_bus(write_enable_bus),
        .o_opcode(opcode),
        .o_we_mem(we_mem),
        .o_load_pc(load_pc),
        .o_load_acc(load_acc),
        .o_load_tmp(load_tmp),
        .o_load_mar(load_mar),
        .o_load_inst(load_inst),
        .o_jmp(jmp),
        .o_imme(imme)
    );

    initial begin
        clk = 1'b0;
        rst = 1'b1;
        inst = 8'b00; // OP ADD/SUB to MEM[0]
        jc = 1'b0;
        jz = 1'b0;

    //CHECKING ADD INST PATH FIRST

    @(posedge clk); // checking state, PC OUT, after reset
    #1
    `assert(write_enable_bus, PC);
    `assert(we_mem, 1'b0);
    `assert(load_pc, 1'b0);
    `assert(load_acc, 1'b0);
    `assert(load_tmp, 1'b0);
    `assert(load_mar, 1'b1);
    `assert(load_inst, 1'b0);
    `assert(jmp, 1'b0);
    `assert(imme, 1'b0);
    
    @(negedge clk); //turns off reset, should start going through states now
    rst = 1'b0;

    @(posedge clk); //State = load IR
    #1
    `assert(write_enable_bus, MEM);
    `assert(we_mem, 1'b0);
    `assert(load_pc, 1'b0);
    `assert(load_acc, 1'b0);
    `assert(load_tmp, 1'b0);
    `assert(load_mar, 1'b0);
    `assert(load_inst, 1'b1);
    `assert(jmp, 1'b0);
    `assert(imme, 1'b0);

    @(posedge clk); // State = Decode (ADD)
    #1
    `assert(write_enable_bus, MEM);
    `assert(we_mem, 1'b0);
    `assert(load_pc, 1'b0);
    `assert(load_acc, 1'b0);
    `assert(load_tmp, 1'b0);
    `assert(load_mar, 1'b1);
    `assert(load_inst, 1'b0);
    `assert(jmp, 1'b0);
    `assert(imme, 1'b0);

    @(posedge clk); // State = Load Tmp
    #1
    `assert(write_enable_bus, MEM);
    `assert(we_mem, 1'b0);
    `assert(load_pc, 1'b0);
    `assert(load_acc, 1'b0);
    `assert(load_tmp, 1'b1);
    `assert(load_mar, 1'b0);
    `assert(load_inst, 1'b0);
    `assert(jmp, 1'b0);
    `assert(imme, 1'b0);

    @(posedge clk); //State = Execute
    #1
    `assert(write_enable_bus, ALU);
    `assert(we_mem, 1'b0);
    `assert(load_pc, 1'b0);
    `assert(load_acc, 1'b1);
    `assert(load_tmp, 1'b0);
    `assert(load_mar, 1'b0);
    `assert(load_inst, 1'b0);
    `assert(jmp, 1'b0);
    `assert(imme, 1'b0);

    @(posedge clk); //State = Increment PC
    #1
    `assert(write_enable_bus, INCREMENTER);
    `assert(we_mem, 1'b0);
    `assert(load_pc, 1'b1);
    `assert(load_acc, 1'b0);
    `assert(load_tmp, 1'b0);
    `assert(load_mar, 1'b0);
    `assert(load_inst, 1'b0);
    `assert(jmp, 1'b0);
    `assert(imme, 1'b0);
    
    @(posedge clk); //State = PC Out
    #1
    `assert(write_enable_bus, PC);
    `assert(we_mem, 1'b0);
    `assert(load_pc, 1'b0);
    `assert(load_acc, 1'b0);
    `assert(load_tmp, 1'b0);
    `assert(load_mar, 1'b1);
    `assert(load_inst, 1'b0);
    `assert(jmp, 1'b0);
    `assert(imme, 1'b0);

    #1
    $display("ADD PATH COMPLETED SUCCESSFULLY");
    

    // ONE FULL CYCLE COMPLETE
    // NOW CHECKING LOAD PATH

    @(negedge clk); //instr set to OP_LOAD to MEM[0]
    inst = {OP_LOAD, 4'b0000};

    @(posedge clk); //State = load IR
    #1
    `assert(write_enable_bus, MEM);
    `assert(we_mem, 1'b0);
    `assert(load_pc, 1'b0);
    `assert(load_acc, 1'b0);
    `assert(load_tmp, 1'b0);
    `assert(load_mar, 1'b0);
    `assert(load_inst, 1'b1);
    `assert(jmp, 1'b0);
    `assert(imme, 1'b0);

    @(posedge clk); // State = Decode (OP_LOAD)
    #1
    `assert(write_enable_bus, MEM);
    `assert(we_mem, 1'b0);
    `assert(load_pc, 1'b0);
    `assert(load_acc, 1'b0);
    `assert(load_tmp, 1'b0);
    `assert(load_mar, 1'b1);
    `assert(load_inst, 1'b0);
    `assert(jmp, 1'b0);
    `assert(imme, 1'b0);

    @(posedge clk); // State = LOAD ACC
    #1 
    `assert(write_enable_bus, MEM);
    `assert(we_mem, 1'b0);
    `assert(load_pc, 1'b0);
    `assert(load_acc, 1'b1);
    `assert(load_tmp, 1'b0);
    `assert(load_mar, 1'b0);
    `assert(load_inst, 1'b0);
    `assert(jmp, 1'b0);
    `assert(imme, 1'b0);

    @(posedge clk); //State = Increment PC
    #1
    `assert(write_enable_bus, INCREMENTER);
    `assert(we_mem, 1'b0);
    `assert(load_pc, 1'b1);
    `assert(load_acc, 1'b0);
    `assert(load_tmp, 1'b0);
    `assert(load_mar, 1'b0);
    `assert(load_inst, 1'b0);
    `assert(jmp, 1'b0);
    `assert(imme, 1'b0);

    @(posedge clk); //State = PC Out
    #1
    `assert(write_enable_bus, PC);
    `assert(we_mem, 1'b0);
    `assert(load_pc, 1'b0);
    `assert(load_acc, 1'b0);
    `assert(load_tmp, 1'b0);
    `assert(load_mar, 1'b1);
    `assert(load_inst, 1'b0);
    `assert(jmp, 1'b0);
    `assert(imme, 1'b0);

    #1
    $display("LOAD PATH COMPLETED SUCCESSFULLY");
    

    //Second Cycle Complete
    //NOW TESTING IMME

    @(posedge clk); //State = load IR
    #1
    `assert(write_enable_bus, MEM);
    `assert(we_mem, 1'b0);
    `assert(load_pc, 1'b0);
    `assert(load_acc, 1'b0);
    `assert(load_tmp, 1'b0);
    `assert(load_mar, 1'b0);
    `assert(load_inst, 1'b1);
    `assert(jmp, 1'b0);
    `assert(imme, 1'b0);

    @(negedge clk); // set inst to imme
    inst = {OP_IMME, 4'b000};

    @(posedge clk); // State = DECODE (Imme) which immediately loads ACC with instr from MEM
    #1
    `assert(write_enable_bus, MEM);
    `assert(we_mem, 1'b0);
    `assert(load_pc, 1'b0);
    `assert(load_acc, 1'b1);
    `assert(load_tmp, 1'b0);
    `assert(load_mar, 1'b0);
    `assert(load_inst, 1'b0);
    `assert(jmp, 1'b0);
    `assert(imme, 1'b1);

    @(posedge clk); // State = Increment PC
    #1
    `assert(write_enable_bus, INCREMENTER);
    `assert(we_mem, 1'b0);
    `assert(load_pc, 1'b1);
    `assert(load_acc, 1'b0);
    `assert(load_tmp, 1'b0);
    `assert(load_mar, 1'b0);
    `assert(load_inst, 1'b0);
    `assert(jmp, 1'b0);
    `assert(imme, 1'b0);

    #1
    $display("IMME PATH COMPLETED SUCCESSFULLY");
    $finish;
    end

    always #5 clk = ~clk;

    always @(posedge clk) begin
        $display("Clock toggled at time %2t, clk = %0b, rst = %0b, inst = %8b, jc = %0b, jz = %0b, write_enable_bus = %8b, opcode = %0b, we_mem = %0b, load_pc = %0b, load_acc = %0b, load_tmp = %0b, load_mar = %0b, load_inst = %0b, jmp = %0b, imme = %0b",               $time, clk, rst, inst, jc, jz, write_enable_bus, opcode, we_mem, load_pc, load_acc, load_tmp, load_mar, load_inst, jmp, imme);
    end

    initial begin 
        $dumpfile("Controller.vcd"); 
        $dumpvars;  
        end 

endmodule

Controller.vcd
$date
	Thu Dec 11 15:27:47 2025
$end
$version
	Icarus Verilog
$end
$timescale
	1ns
$end
$scope module controller_tb $end
$var wire 8 ! write_enable_bus [7:0] $end
$var wire 1 " we_mem $end
$var wire 1 # opcode $end
$var wire 1 $ load_tmp $end
$var wire 1 % load_pc $end
$var wire 1 & load_mar $end
$var wire 1 ' load_inst $end
$var wire 1 ( load_acc $end
$var wire 1 ) jmp $end
$var wire 1 * imme $end
$var parameter 8 + ACC $end
$var parameter 8 , ALU $end
$var parameter 32 - DATA_WIDTH $end
$var parameter 8 . DECODER $end
$var parameter 8 / INCREMENTER $end
$var parameter 8 0 MEM $end
$var parameter 4 1 OP_ADD $end
$var parameter 4 2 OP_IMME $end
$var parameter 4 3 OP_JC $end
$var parameter 4 4 OP_JMP $end
$var parameter 4 5 OP_JZ $end
$var parameter 4 6 OP_LOAD $end
$var parameter 4 7 OP_STORE $end
$var parameter 4 8 OP_SUB $end
$var parameter 8 9 PC $end
$var parameter 8 : TMP $end
$var reg 1 ; clk $end
$var reg 8 < inst [7:0] $end
$var reg 1 = jc $end
$var reg 1 > jz $end
$var reg 1 ? rst $end
$scope module dut $end
$var wire 1 ; i_clk $end
$var wire 8 @ i_inst [7:0] $end
$var wire 1 = i_jc $end
$var wire 1 > i_jz $end
$var wire 1 ? i_rst $end
$var parameter 8 A ACC $end
$var parameter 8 B ALU $end
$var parameter 32 C DATA_WIDTH $end
$var parameter 3 D DECODE $end
$var parameter 8 E DECODER $end
$var parameter 3 F EXECUTE $end
$var parameter 8 G INCREMENTER $end
$var parameter 3 H INCREMENT_PC $end
$var parameter 3 I LOAD_ACC $end
$var parameter 3 J LOAD_IR $end
$var parameter 3 K LOAD_TMP $end
$var parameter 8 L MEM $end
$var parameter 4 M OP_ADD $end
$var parameter 4 N OP_IMME $end
$var parameter 4 O OP_JC $end
$var parameter 4 P OP_JMP $end
$var parameter 4 Q OP_JZ $end
$var parameter 4 R OP_LOAD $end
$var parameter 4 S OP_STORE $end
$var parameter 4 T OP_SUB $end
$var parameter 8 U PC $end
$var parameter 3 V PC_OUT $end
$var parameter 3 W STORE_MEM $end
$var parameter 8 X TMP $end
$var reg 3 Y next_state [2:0] $end
$var reg 1 * o_imme $end
$var reg 1 ) o_jmp $end
$var reg 1 ( o_load_acc $end
$var reg 1 ' o_load_inst $end
$var reg 1 & o_load_mar $end
$var reg 1 % o_load_pc $end
$var reg 1 $ o_load_tmp $end
$var reg 1 # o_opcode $end
$var reg 1 " o_we_mem $end
$var reg 8 Z o_write_enable_bus [7:0] $end
$var reg 1 [ opcode $end
$var reg 3 \ state [2:0] $end
$upscope $end
$upscope $end
$enddefinitions $end
$comment Show the parameter values. $end
$dumpall
b100000 X
b110 W
b0 V
b1 U
b1 T
b11 S
b10 R
b111 Q
b101 P
b110 O
b100 N
b0 M
b100 L
b100 K
b1 J
b101 I
b111 H
b10 G
b11 F
b1000000 E
b10 D
b1000 C
b1000 B
b10000 A
b100000 :
b1 9
b1 8
b11 7
b10 6
b111 5
b101 4
b110 3
b100 2
b0 1
b100 0
b10 /
b1000000 .
b1000 -
b1000 ,
b10000 +
$end
#0
$dumpvars
b0 \
0[
b1 Z
b1 Y
b0 @
1?
0>
0=
b0 <
0;
0*
0)
0(
0'
1&
0%
0$
0#
0"
b1 !
$end
#5
1;
#10
0?
0;
#15
b10 Y
1'
b100 !
b100 Z
0&
b1 \
1;
#20
0;
#25
b100 Y
1&
0'
b10 \
1;
#30
0;
#35
b11 Y
1$
0&
1[
b100 \
1;
#40
0;
#45
b111 Y
1(
b1000 !
b1000 Z
1#
0$
b11 \
1;
#50
0;
#55
b0 Y
1%
b10 !
b10 Z
0(
0#
b111 \
1;
#60
0;
#65
b1 Y
1&
b1 !
b1 Z
0%
b0 \
1;
#70
1&
b1 Y
b100000 <
b100000 @
0;
#75
b10 Y
1'
b100 !
b100 Z
0&
b1 \
1;
#80
0;
#85
b101 Y
1&
0'
b10 \
1;
#90
0;
#95
b111 Y
1(
0&
0[
b101 \
1;
#100
0;
#105
b0 Y
1%
b10 !
b10 Z
0(
b111 \
1;
#110
0;
#115
b1 Y
1&
b1 !
b1 Z
0%
b0 \
1;
#120
0;
#125
b10 Y
1'
b100 !
b100 Z
0&
b1 \
1;
#130
1'
b10 Y
b1000000 <
b1000000 @
0;
#135
b111 Y
1(
1*
0'
b10 \
1;
#140
0;
#145
b0 Y
1%
b10 !
b10 Z
0*
0(
b111 \
1;
