src/regfile.v
module Register #(
    parameter DATA_WIDTH = 8
) (
    // input
    input wire i_clk,
    input wire i_rst,
    input wire i_we,
    input wire i_bus_writable,
    // output
    output [DATA_WIDTH-1 : 0] o_data,
    // input and output
    inout [DATA_WIDTH-1 : 0] io_data
);

    reg [DATA_WIDTH-1:0] register;

    always @(posedge i_clk or posedge i_rst) begin
        if (i_rst) begin  
            register <= {DATA_WIDTH{1'b0}}; //resets all bits to 0
        end 
        else if (i_we) begin
            register <= io_data; //if write enabled, on posedge of clk reg = io_data
        end 
    end
assign o_data = register;
assign io_data = (i_bus_writable) ? register : {DATA_WIDTH{1'bz}}; //only drives bus when allowed
endmodule

tb/Register_tb.v
`default_nettype none 
 `timescale 1ns/1ns 

 `define assert(signal, value) \ 
     if (signal !== value) begin \ 
         $display("ASSERTION FAILED at %2d in %m: signal != value", $time); \ 
         $finish; \ 
     end 

 module register_tb; 
   localparam integer DATA_WIDTH = 8; 

   reg clk; 
   reg rst;  
   reg we; 
   reg bus_writable;  

   wire [7:0] o_data; 

   reg [DATA_WIDTH-1:0] io_data_driver; // Register to drive the inout signal 
   wire [DATA_WIDTH-1:0] io_data;       // Wire to read the inout signal 
   reg io_data_drive_enable;            // Control signal to enable driving the inout signal 

   // Conditionally drive the inout signal 
   assign io_data = io_data_drive_enable ? io_data_driver : {DATA_WIDTH{1'bz}}; 

   Register #(.DATA_WIDTH(DATA_WIDTH)) dut ( 
     .i_clk(clk), 
     .i_rst(rst), 
     .i_we(we), 
     .i_bus_writable(bus_writable), 
     .o_data(o_data), 
     .io_data(io_data) 
   ); 

   initial begin 
     // Initialize signals 
     clk = 0; 
     rst = 1; 
     we = 0; 
     bus_writable = 0; 
     io_data_driver = 8'h00; 
     io_data_drive_enable = 0; 

     #5 // Release reset and perform operations 
     	rst = 0; 
     	`assert(dut.i_rst, 1'b0); 
     	`assert(io_data, 8'bzzzzzzz); 
     	`assert(dut.io_data, 8'bzzzzzzz); 
     #10 // Example operation: driving the inout port 
     	io_data_driver = 8'hA5; 
         io_data_drive_enable = 1'b1; 
        	we = 1'b1; 
     	`assert(dut.o_data, 8'b00000000); 
     #10 io_data_drive_enable = 0; 
     	io_data_driver = 8'h00; 
     	bus_writable = 1'b1; 
 		we = 1'b0; 
     	`assert(dut.o_data, 8'b10100101); 
     	`assert(dut.io_data, 8'b10100101); 
     	`assert(dut.i_bus_writable, 1'b1); 
     	`assert(io_data, 8'b10100101); 
     #10 // Disconnect bus 
     	io_data_drive_enable = 0; 
     	io_data_driver = 8'h00; 
     	bus_writable = 1'b0; 
     	we = 1'b0; 
     	`assert(dut.o_data, 8'b10100101); 
     	`assert(dut.io_data, 8'b10100101); 
     #10 
     	io_data_drive_enable = 1; 
     	io_data_driver = 8'h00; 
     	bus_writable = 1'b0; 
     	we = 1'b1; 
     	`assert(dut.o_data, 8'b10100101); 
     #10 
     	io_data_drive_enable = 0; 
     	io_data_driver = 8'hA5; 
     	bus_writable = 1'b1; 
     	we = 1'b0; 
     	`assert(dut.o_data, 8'b00000000); 
     	`assert(dut.io_data, 8'b00000000); 
     	`assert(io_data, 8'b00000000); 
 	#5; 
     	$display("Testbench Passed!"); 
     	$finish; 
   end 

   // Clock generation 
   always #5 clk = ~clk; 

   always @(posedge clk) begin 
       $display("Clock toggled at time %2t, clk = %0b, rst = %0b, we = %0b, bus_writable = %0b, o_data = %8b, io_data = %8b",		$time, clk, rst, we, bus_writable, o_data, io_data); 
   end 

   initial begin 
     $dumpfile("register.vcd"); 
     $dumpvars;  
   end 
 endmodule

register.vcd
$date
	Fri Nov 28 21:39:28 2025
$end
$version
	Icarus Verilog
$end
$timescale
	1ns
$end
$scope module register_tb $end
$var wire 8 ! io_data [7:0] $end
$var wire 8 " o_data [7:0] $end
$var parameter 32 # DATA_WIDTH $end
$var reg 1 $ bus_writable $end
$var reg 1 % clk $end
$var reg 1 & io_data_drive_enable $end
$var reg 8 ' io_data_driver [7:0] $end
$var reg 1 ( rst $end
$var reg 1 ) we $end
$scope module dut $end
$var wire 1 $ i_bus_writable $end
$var wire 1 % i_clk $end
$var wire 1 ( i_rst $end
$var wire 1 ) i_we $end
$var wire 8 * io_data [7:0] $end
$var wire 8 + o_data [7:0] $end
$var parameter 32 , DATA_WIDTH $end
$var reg 8 - register [7:0] $end
$upscope $end
$upscope $end
$enddefinitions $end
$comment Show the parameter values. $end
$dumpall
b1000 ,
b1000 #
$end
#0
$dumpvars
b0 -
b0 +
bz *
0)
1(
b0 '
0&
0%
0$
b0 "
bz !
$end
#5
1%
0(
#10
0%
#15
b10100101 "
b10100101 +
b10100101 -
b10100101 !
b10100101 *
1%
1)
1&
b10100101 '
#20
0%
#25
b10100101 !
b10100101 *
1%
0)
1$
b0 '
0&
#30
0%
#35
bz !
bz *
1%
0$
#40
0%
#45
b0 "
b0 +
b0 -
b0 !
b0 *
1%
1)
1&
#50
0%
#55
b0 !
b0 *
1%
0)
1$
b10100101 '
0&
#60
0%
#65
b10100101 !
b10100101 *
1%
0$
1&
