src/Register.v
module Register #(
    parameter DATA_WIDTH = 8
) (
    // input
    input wire i_clk,
    input wire i_rst,
    input wire i_we,
    input wire i_bus_writable,
    // output
    output [DATA_WIDTH-1 : 0] o_pc,
    // input and output
    inout [DATA_WIDTH-1 : 0] io_data
);

    reg [DATA_WIDTH-1:0] register;

    always @(posedge i_clk or posedge i_rst) begin
        if (i_rst) begin  
            register <= {DATA_WIDTH{1'b0}};                                 //resets all bits to 0
        end 
        else if (i_we) begin
            register <= io_data;                                            //if write enabled, on posedge of clk register = io_data
        end 
    end
assign o_pc = register;
assign io_data = (i_bus_writable) ? register : {DATA_WIDTH{1'bz}};          //when bus is writeable io_data = register
endmodule

src/Alu.v
module Alu #(
    parameter DATA_WIDTH = 8
) (
    //inputs
    input i_clk,
    input i_rst,
    input i_opcode,
    input i_bus_writable,
    input [DATA_WIDTH-1:0] i_a,
    input [DATA_WIDTH-1:0] i_b,
    //outputs
    output reg o_jc,
    output reg o_jz,
    output wire [DATA_WIDTH-1:0] o_c
);

    reg carry;
    reg [DATA_WIDTH-1:0] tmp;

    always @ (posedge i_clk or posedge i_rst) begin 
        if (i_rst) begin
            o_jc <= 1'b0;                   //rst will set both jc and jz to 0
            o_jz <= 1'b0;
        end
        else if (i_bus_writable) begin
            o_jc <= carry;                  // when carry bit is needed for adition or subtraction it will be stored
            if (tmp == 0 && !i_opcode)
            o_jz <= 1'b1;                   // when a - b = 0 jz will be set to 1
            else
            o_jz <= 1'b0;
        end
    end

    always@(*) begin
        if (i_opcode) begin
            {carry,tmp} = i_a + i_b;        //addition
        end
        else begin
            {carry,tmp} = i_a - i_b;        //subtraction
        end
    end

    assign o_c = i_bus_writable ? tmp : {DATA_WIDTH{1'bz}};

endmodule

src/Ram.v
module Ram #(
    parameter DATA_WIDTH = 8,
    parameter MEM_SIZE = 16
) (
    //inputs
    input i_clk,
    input i_we,
    input i_bus_writable,
    input i_jmp_imme,
    input [DATA_WIDTH-1:0] i_addr,
    //inout
    inout [DATA_WIDTH-1:0] io_data
);

reg [DATA_WIDTH-1:0] mem [0:MEM_SIZE-1];
wire [DATA_WIDTH-1:0] out; 

always @ (posedge i_clk) begin
    if (i_we) mem[i_addr[3:0]] <= io_data;
end 

assign out = (i_jmp_imme) ? {4'h0, mem[i_addr[3:0]][3:0]} : mem[i_addr[3:0]];
assign io_data = (i_bus_writable) ? out : {DATA_WIDTH{1'bz}};

endmodule

src/Incrementer.v
module Incrementer #(
    parameter DATA_WIDTH = 8
) (
    input [DATA_WIDTH-1:0] i_pc,
    input i_bus_writable,
    output [DATA_WIDTH-1:0] o_pc
);

    assign o_pc = (i_bus_writable) ? (i_pc + 1'b1) : {DATA_WIDTH{1'bz}};

endmodule

src/Controller.v
module Controller #(
    parameter DATA_WIDTH = 8
) (
    //inputs
    input i_clk,
    input i_rst,
    input [DATA_WIDTH-1:0] i_inst,
    input i_jc,
    input i_jz,
    //output
    output reg [7:0] o_write_enable_bus,
    output reg o_opcode,
    output reg o_we_mem,
    output reg o_load_pc,
    output reg o_load_tmp,
    output reg o_load_mar,
    output reg o_load_inst,
    output reg o_load_acc,
    output reg o_jmp,
    output reg o_imme
);
    // DEFINE INSTRUCTION SET (top 4 pits of i_inst[7:4])
    localparam OP_ADD   = 4'b0000;
    localparam OP_SUB   = 4'b0001;
    localparam OP_LOAD  = 4'b0010;
    localparam OP_STORE = 4'b0011;
    localparam OP_IMME  = 4'b0100;
    localparam OP_JMP   = 4'b0101;
    localparam OP_JC    = 4'b0110;
    localparam OP_JZ    = 4'b0111;

    //STATES
    localparam PC_OUT       = 3'b000;
    localparam LOAD_IR      = 3'b001;
    localparam DECODE       = 3'b010;
    localparam EXECUTE      = 3'b011;
    localparam LOAD_TMP     = 3'b100;
    localparam LOAD_ACC     = 3'b101;
    localparam STORE_MEM    = 3'b110;
    localparam INCREMENT_PC = 3'b111;

    //write_enable_bus
    localparam PC           = 8'b0000_0001;
    localparam INCREMENTER  = 8'b0000_0010;
    localparam MEM          = 8'b0000_0100;
    localparam ALU          = 8'b0000_1000;
    localparam ACC          = 8'b0001_0000;
    localparam TMP          = 8'b0010_0000;
    localparam DECODER      = 8'b0100_0000;

    reg [2:0] state = PC_OUT;
    reg [2:0] next_state = PC_OUT;
    reg opcode;

    //on clock cycle or reset
    always @ (posedge i_clk or posedge i_rst) begin
        if (i_rst) begin 
            state <= PC_OUT;
            opcode <= 1'b0;
        end
        else begin
            state <= next_state;
            if (state == DECODE) begin
                if(i_inst[7:4] == OP_ADD) begin
                    opcode <= 1'b1;
                end
                else begin
                    opcode <= 1'b0; 
                end                   
            end
        end 
    end

    //FSM
    always @(*) begin
        next_state = state;                              
        o_load_pc   = 1'b0;
        o_load_mar  = 1'b0;
        o_opcode    = 1'b0;
        o_we_mem    = 1'b0;
        o_load_acc  = 1'b0;
        o_load_tmp  = 1'b0;
        o_jmp       = 1'b0;
        o_imme      = 1'b0;
        o_load_inst = 1'b0;
        case (state)
        PC_OUT: begin
            o_write_enable_bus = PC;
            o_load_mar = 1'b1;
            next_state = LOAD_IR;
        end
        LOAD_IR : begin
            o_write_enable_bus = MEM;
            o_load_inst = 1'b1;
            next_state = DECODE;
        end
        DECODE: begin
            o_write_enable_bus = MEM;
            case (i_inst[7:4])
            OP_ADD,OP_SUB: begin
                o_load_mar = 1'b1;
                next_state = LOAD_TMP;
            end
            OP_LOAD: begin
                o_load_mar = 1'b1;
                next_state = LOAD_ACC;
            end
            OP_STORE: begin
                o_load_mar = 1'b1;
                next_state = STORE_MEM;
            end
            OP_IMME: begin
                o_imme = 1'b1;
                o_load_acc = 1'b1;
                next_state = INCREMENT_PC;
            end
            OP_JMP: begin
                o_jmp = 1'b1;
                o_load_pc = 1'b1;
                next_state = PC_OUT;
            end
            OP_JC: begin
                if (i_jc) begin
                    o_jmp = 1'b1;
                    o_load_pc = 1'b1;
                    next_state = PC_OUT; 
                end
                else begin
                    next_state = INCREMENT_PC;
                    end
            end
            OP_JZ: begin
                if (i_jz) begin
                    o_jmp = 1'b1;
                    o_load_pc = 1'b1;
                    next_state = PC_OUT; 
                end
                else begin
                    next_state = INCREMENT_PC;
                    end
            end
            default : begin
                $display ("Should not end here!");
            end
            endcase
        end
        LOAD_TMP: begin
            o_write_enable_bus = MEM;
            o_load_tmp = 1'b1;
            next_state = EXECUTE;
        end
        EXECUTE: begin
            o_opcode = opcode;
            o_write_enable_bus = ALU;
            o_load_acc = 1'b1;
            next_state = INCREMENT_PC;
        end
        LOAD_ACC: begin
            o_write_enable_bus = MEM;
            o_load_acc = 1'b1;
            next_state = INCREMENT_PC;
        end
        STORE_MEM: begin
            o_write_enable_bus = ACC;
            o_we_mem = 1'b1;
            next_state = INCREMENT_PC; 
        end 
        INCREMENT_PC: begin
            o_write_enable_bus = INCREMENTER;
            o_load_pc = 1'b1;
            next_state = PC_OUT;
        end
        endcase
    end
endmodule

src/Top.v
`default_nettype none
`timescale 1ns/1ns

module Top #(
    parameter DATA_WIDTH = 8
) (
    //inputs
    input clk,
    input rst,
    //output
    output [DATA_WIDTH-1:0] debug
);

    wire [4:0] write_enable_bus;
    wire opcode;
    wire we_mem;
    wire load_pc;
    wire load_acc;
    wire load_tmp;
    wire load_mar;
    wire load_imme;
    wire load_jmp;
    wire load_inst;
    wire [DATA_WIDTH-1:0] o_tmp;
    wire [DATA_WIDTH-1:0] o_acc;
    wire [DATA_WIDTH-1:0] bus;
    wire [DATA_WIDTH-1:0] o_pc;
    wire [DATA_WIDTH-1:0] o_mar;
    wire [DATA_WIDTH-1:0] inst;
    wire jc;
    wire jz;

    Controller #( 
        .DATA_WIDTH(DATA_WIDTH)
    ) ctrl (
        .i_clk(clk),
        .i_rst(rst),
        .i_inst(inst),
        .i_jz(jz),
        .i_jc(jc),
        .o_write_enable_bus(write_enable_bus),
        .o_opcode(opcode),
        .o_we_mem(we_mem),
        .o_load_pc(load_pc),
        .o_load_acc(load_acc),
        .o_load_inst(load_inst),
        .o_load_mar(load_mar),
        .o_load_tmp(load_tmp),
        .o_jmp(load_jmp),
        .o_imme(load_imme)
    );

    Register #(
        .DATA_WIDTH(DATA_WIDTH)
    ) pc_reg (
        .i_clk(clk),
        .i_rst(rst),
        .i_we(load_pc),
        .i_bus_writable(write_enable_bus[0]),
        .o_pc(o_pc),                                //change to .o_data after testing
        .io_data(bus)
    );

    Incrementer #(
      .DATA_WIDTH(DATA_WIDTH)
    ) inc (
      .i_pc(o_pc),
      .i_bus_writable(write_enable_bus[1]),
      .o_pc(bus)
    );

    Ram #(
        .DATA_WIDTH(DATA_WIDTH)
    ) ram (
        .i_clk(clk),
        .i_we(we_mem),
        .i_bus_writable(write_enable_bus[2]),
        .i_jmp_imme(load_jmp | load_imme),
        .i_addr(o_mar),
        .io_data(bus)
    );

    Register #(
      .DATA_WIDTH(DATA_WIDTH)
    ) mar (
      .i_clk(clk),
      .i_rst(rst),
      .i_we(load_mar),
      .i_bus_writable(1'b0),
      .o_pc(o_mar),
      .io_data(bus)
    );

    Register #(
      .DATA_WIDTH(DATA_WIDTH)
    ) ir (
      .i_clk(clk),
      .i_rst(rst),
      .i_we(load_inst),
      .i_bus_writable(1'b0),
      .o_pc(inst),
      .io_data(bus)
    );

     Alu #(
      .DATA_WIDTH(DATA_WIDTH)
    ) alu (
      .i_clk(clk),
      .i_rst(rst),
      .i_a(o_acc),
      .i_b(o_tmp),
      .i_opcode(opcode),
      .i_bus_writable(write_enable_bus[3]),
      .o_c(bus),
      .o_jc(jc),
      .o_jz(jz)
    ); 

      Register #(
      .DATA_WIDTH(DATA_WIDTH)
    ) acc (
      .i_clk(clk),
      .i_rst(rst),
      .i_we(load_acc),
      .i_bus_writable(write_enable_bus[4]),
      .o_pc(o_acc),
      .io_data(bus)
    );

    assign debug = bus;

    Register #(
      .DATA_WIDTH(DATA_WIDTH)
    ) tmp (
      .i_clk(clk),
      .i_rst(rst),
      .i_we(load_tmp),
      .i_bus_writable(1'b0),
      .o_pc(o_tmp),
      .io_data(bus)
    );

endmodule

tb/Top_tb.v
`default_nettype none 
`timescale 1ns / 1ns

`define assert(signal, value) \
        if (signal !== value) begin \
            $display("ASSERTION FAILED at %2d in %m: signal != value", $time); \
            $finish; \
        end

module top_tb;

  localparam integer DATA_WIDTH = 8;

  reg clk;
  reg rst;
  wire [7:0] debug;

  Top #(
      .DATA_WIDTH(DATA_WIDTH)
  ) dut (
      .clk  (clk),
      .rst  (rst),
      .debug(debug)
  );

  always #5 clk = ~clk;

  initial begin
    clk = 1'b1;
    rst = 1'b1;
  end

  initial begin
    $display("+------------------------------------------+");
    $display("|   RUN FIRST TESTBENCH - INITIALIZE RAM   |");
    $display("+------------------------------------------+");

    //CODE
    dut.ram.mem[0] = 8'b0010_1111;  //LOAD  (0x2F) ACC      = MEM[0xF]
    dut.ram.mem[1] = 8'b0000_1110;  //ADD   (0x0E) ACC      = ACC + MEW[0xE] (4 + 1)
    dut.ram.mem[2] = 8'b0011_1101;  //STORE (0x3D) MEM[0xD] = ACC
    dut.ram.mem[3] = 8'b0001_1110;  //SUB   (0x1E) ACC      = ACC - MEM[0xE] (5 - 1)
    dut.ram.mem[4] = 8'b0010_1101;  //LOAD  (0x2D) ACC      = MEM[0xD]
    dut.ram.mem[5] = 8'b0011_1000;  //STORE (0x38) MEM[0x8] = ACC
    dut.ram.mem[6] = 8'b0111_0000;  //JZ    (0x70) PC       = 0x00
    dut.ram.mem[7] = 8'b0000_0000;
    //DATA
    dut.ram.mem[8] = 8'b00000000;
    dut.ram.mem[9] = 8'b00000000;
    dut.ram.mem[10] = 8'b00000000;
    dut.ram.mem[11] = 8'b00000000;
    dut.ram.mem[12] = 8'b00000000;
    dut.ram.mem[13] = 8'b00000000;
    dut.ram.mem[14] = 8'b00000001; //(MEM[0xE]=0x01)
    dut.ram.mem[15] = 8'b00000100; //(MEM[0xF]=0x04)

    rst = 1'b1;
    #10;
    rst = 1'b0;
    #360;

    `assert(dut.ram.mem[8], 8'b00000101);
    `assert(dut.ram.mem[9], 8'b00000000);
    `assert(dut.ram.mem[10], 8'b0000000);
    `assert(dut.ram.mem[11], 8'b0000000);
    `assert(dut.ram.mem[12], 8'b0000000);
    `assert(dut.ram.mem[13], 8'b00000101);
    `assert(dut.ram.mem[14], 8'b00000001);
    `assert(dut.ram.mem[15], 8'b00000100);

    $display("");
    $display("+------------------------------------------+");
    $display("|   RUN SECOND TESTBENCH - INITIALIZE RAM   |");
    $display("+------------------------------------------+");

    //CODE
    dut.ram.mem[0] = 8'b0010_1111;  //LOAD  (0x2F) ACC      = MEM[0xF]
    dut.ram.mem[1] = 8'b0000_1110;  //ADD   (0x0E) ACC      = ACC + MEW[0xE] (15 + 2)
    dut.ram.mem[2] = 8'b0110_0101;  //JC    (0x65) PC       = 0x05
    dut.ram.mem[3] = 8'b0001_1110;  //SUB   (0x1E) ACC      = ACC - MEM[0xE] (15 - 2)
    dut.ram.mem[4] = 8'b0010_1101;  //LOAD  (0x2D) ACC      = MEM[0xD]
    dut.ram.mem[5] = 8'b0011_1000;  //STORE (0x38) MEM[0x8] = ACC
    dut.ram.mem[6] = 8'b0001_1101;  //SUB   (0x1D) ACC      = ACC - MEM[0xD] (1-1)
    dut.ram.mem[7] = 8'b0111_0000;  //JZ    (0x70) PC       = 0x00
    //DATA
    dut.ram.mem[8] = 8'b00000000;
    dut.ram.mem[9] = 8'b00000000;
    dut.ram.mem[10] = 8'b00000000;
    dut.ram.mem[11] = 8'b00000000;
    dut.ram.mem[12] = 8'b00000000;
    dut.ram.mem[13] = 8'b00000001;  //(MEM[0xD]=0x01)
    dut.ram.mem[14] = 8'b00000010;  //(MEM[0xE]=0x02)
    dut.ram.mem[15] = 8'b11111111;  //(MEM[0xF]=0xFF) 

    rst = 1'b1;
    #10;
    rst = 1'b0;
    #320;

    `assert(dut.ram.mem[8], 8'b00000001);
    `assert(dut.ram.mem[9], 8'b00000000);
    `assert(dut.ram.mem[10], 8'b0000000);
    `assert(dut.ram.mem[11], 8'b0000000);
    `assert(dut.ram.mem[12], 8'b0000000);
    `assert(dut.ram.mem[13], 8'b00000001);
    `assert(dut.ram.mem[14], 8'b00000010);
    `assert(dut.ram.mem[15], 8'b11111111);

    $display("");
    $display("+------------------------------------------+");
    $display("|   RUN THIRD TESTBENCH - INITIALIZE RAM   |");
    $display("+------------------------------------------+");
    //CODE
    dut.ram.mem[0] = 8'b0100_1111;  //LOAD  (0x4F) ACC      = IMME(#15)
    dut.ram.mem[1] = 8'b0000_1101;  //ADD   (0x0D) ACC      = ACC + MEM[0xD] (15 + 1)
    dut.ram.mem[2] = 8'b0110_0101;  //JC    (0x65) PC       = 0x05 
    dut.ram.mem[3] = 8'b0001_1110;  //SUB   (0x1E) ACC      = ACC - MEM[0xE] (15 - 2)
    dut.ram.mem[4] = 8'b0011_1001;  //STORE (0x39) MEM[0x9] = ACC
    dut.ram.mem[5] = 8'b0011_1000;  //STORE (0x38) MEM[0x8] = ACC
    dut.ram.mem[6] = 8'b0001_1000;  //SUB   (0x18) ACC      = ACC - MEM[0x8] (1-1)
    dut.ram.mem[7] = 8'b0111_0000;  //JZ    (0x70) PC       = 0x00
    //DATA
    dut.ram.mem[8] = 8'b00001111;
    dut.ram.mem[9] = 8'b00000000;
    dut.ram.mem[10] = 8'b00000000;
    dut.ram.mem[11] = 8'b00000000;
    dut.ram.mem[12] = 8'b00000000;
    dut.ram.mem[13] = 8'b00000001;  //(MEM[0xD]=0x01)
    dut.ram.mem[14] = 8'b00000010;  //(MEM[0xE]=0x02)
    dut.ram.mem[15] = 8'b11111111;  //(MEM[0xF]=0xFF) 

    rst = 1'b1;
    #10;
    rst = 1'b0;
    #420;

    `assert(dut.ram.mem[8], 8'b00001110);
    `assert(dut.ram.mem[9], 8'b00001110);
    `assert(dut.ram.mem[10], 8'b0000000);
    `assert(dut.ram.mem[11], 8'b0000000);
    `assert(dut.ram.mem[12], 8'b0000000);
    `assert(dut.ram.mem[13], 8'b00000001);
    `assert(dut.ram.mem[14], 8'b00000010);
    `assert(dut.ram.mem[15], 8'b11111111);
    $finish;

  end

  task print_ram;
    integer i;
    begin
      $display("Print RAM");
      for (i = 0; i < 16; i = i + 1) begin
        $display("ram[%0d]: %b", i, dut.ram.mem[i]);  // Accessing the DUT's RAM memory
      end
    end
  endtask

  // Define parameters for fixed string representations
  reg [0:31] PC = "PC";
  reg [0:31] INCR = "INCR";
  reg [0:31] MEM = "MEM";
  reg [0:31] ALU = "ALU";
  reg [0:31] ACC = "ACC";
  reg [0:31] TMP = "TMP";
  reg [0:31] CONTROLER = "CTRL";
  reg [0:31] UNKNOWN = "UKNW";

  always @(posedge clk) begin
    $display(
        "Time %2t, clk = %b, rst = %b, pc_reg = %2h, bus_access = %s, acc_reg = %2h, ir_reg = %2h",
        $time, clk, rst, dut.pc_reg.register, get_write_access_string(dut.ctrl.o_write_enable_bus),
        dut.acc.register, dut.ir.register);
  end

  // Function to get string representation of write_access
  function [31:0] get_write_access_string(input [7:0] access);
    begin
      case (access)
        8'h01:   get_write_access_string = PC;
        8'h02:   get_write_access_string = INCR;
        8'h04:   get_write_access_string = MEM;
        8'h08:   get_write_access_string = ALU;
        8'h10:   get_write_access_string = ACC;
        8'h20:   get_write_access_string = TMP;
        8'h40:   get_write_access_string = CONTROLER;
        default: get_write_access_string = UNKNOWN;
      endcase
    end
  endfunction

  
  initial begin
    $dumpfile("top_tb.vcd");
    $dumpvars;
  end

endmodule

top_tb.vcd
$date
	Fri Jan 09 11:15:46 2026
$end
$version
	Icarus Verilog
$end
$timescale
	1ns
$end
$scope module top_tb $end
$var wire 8 ! debug [7:0] $end
$var parameter 32 " DATA_WIDTH $end
$var reg 32 # ACC [0:31] $end
$var reg 32 $ ALU [0:31] $end
$var reg 32 % CONTROLER [0:31] $end
$var reg 32 & INCR [0:31] $end
$var reg 32 ' MEM [0:31] $end
$var reg 32 ( PC [0:31] $end
$var reg 32 ) TMP [0:31] $end
$var reg 32 * UNKNOWN [0:31] $end
$var reg 1 + clk $end
$var reg 1 , rst $end
$scope function get_write_access_string $end
$var reg 8 - access [7:0] $end
$upscope $end
$scope module dut $end
$var wire 8 . bus [7:0] $end
$var wire 1 + clk $end
$var wire 8 / debug [7:0] $end
$var wire 1 , rst $end
$var wire 5 0 write_enable_bus [4:0] $end
$var wire 1 1 we_mem $end
$var wire 1 2 opcode $end
$var wire 8 3 o_tmp [7:0] $end
$var wire 8 4 o_pc [7:0] $end
$var wire 8 5 o_mar [7:0] $end
$var wire 8 6 o_acc [7:0] $end
$var wire 1 7 load_tmp $end
$var wire 1 8 load_pc $end
$var wire 1 9 load_mar $end
$var wire 1 : load_jmp $end
$var wire 1 ; load_inst $end
$var wire 1 < load_imme $end
$var wire 1 = load_acc $end
$var wire 1 > jz $end
$var wire 1 ? jc $end
$var wire 8 @ inst [7:0] $end
$var parameter 32 A DATA_WIDTH $end
$scope module acc $end
$var wire 1 B i_bus_writable $end
$var wire 1 + i_clk $end
$var wire 1 , i_rst $end
$var wire 8 C io_data [7:0] $end
$var wire 8 D o_pc [7:0] $end
$var wire 1 = i_we $end
$var parameter 32 E DATA_WIDTH $end
$var reg 8 F register [7:0] $end
$upscope $end
$scope module alu $end
$var wire 8 G i_a [7:0] $end
$var wire 1 H i_bus_writable $end
$var wire 1 + i_clk $end
$var wire 1 , i_rst $end
$var wire 8 I o_c [7:0] $end
$var wire 1 2 i_opcode $end
$var wire 8 J i_b [7:0] $end
$var parameter 32 K DATA_WIDTH $end
$var reg 1 L carry $end
$var reg 1 ? o_jc $end
$var reg 1 > o_jz $end
$var reg 8 M tmp [7:0] $end
$upscope $end
$scope module ctrl $end
$var wire 1 + i_clk $end
$var wire 1 ? i_jc $end
$var wire 1 > i_jz $end
$var wire 1 , i_rst $end
$var wire 8 N i_inst [7:0] $end
$var parameter 8 O ACC $end
$var parameter 8 P ALU $end
$var parameter 32 Q DATA_WIDTH $end
$var parameter 3 R DECODE $end
$var parameter 8 S DECODER $end
$var parameter 3 T EXECUTE $end
$var parameter 8 U INCREMENTER $end
$var parameter 3 V INCREMENT_PC $end
$var parameter 3 W LOAD_ACC $end
$var parameter 3 X LOAD_IR $end
$var parameter 3 Y LOAD_TMP $end
$var parameter 8 Z MEM $end
$var parameter 4 [ OP_ADD $end
$var parameter 4 \ OP_IMME $end
$var parameter 4 ] OP_JC $end
$var parameter 4 ^ OP_JMP $end
$var parameter 4 _ OP_JZ $end
$var parameter 4 ` OP_LOAD $end
$var parameter 4 a OP_STORE $end
$var parameter 4 b OP_SUB $end
$var parameter 8 c PC $end
$var parameter 3 d PC_OUT $end
$var parameter 3 e STORE_MEM $end
$var parameter 8 f TMP $end
$var reg 3 g next_state [2:0] $end
$var reg 1 < o_imme $end
$var reg 1 : o_jmp $end
$var reg 1 = o_load_acc $end
$var reg 1 ; o_load_inst $end
$var reg 1 9 o_load_mar $end
$var reg 1 8 o_load_pc $end
$var reg 1 7 o_load_tmp $end
$var reg 1 2 o_opcode $end
$var reg 1 1 o_we_mem $end
$var reg 8 h o_write_enable_bus [7:0] $end
$var reg 1 i opcode $end
$var reg 3 j state [2:0] $end
$upscope $end
$scope module inc $end
$var wire 1 k i_bus_writable $end
$var wire 8 l o_pc [7:0] $end
$var wire 8 m i_pc [7:0] $end
$var parameter 32 n DATA_WIDTH $end
$upscope $end
$scope module ir $end
$var wire 1 o i_bus_writable $end
$var wire 1 + i_clk $end
$var wire 1 , i_rst $end
$var wire 1 ; i_we $end
$var wire 8 p io_data [7:0] $end
$var wire 8 q o_pc [7:0] $end
$var parameter 32 r DATA_WIDTH $end
$var reg 8 s register [7:0] $end
$upscope $end
$scope module mar $end
$var wire 1 t i_bus_writable $end
$var wire 1 + i_clk $end
$var wire 1 , i_rst $end
$var wire 1 9 i_we $end
$var wire 8 u io_data [7:0] $end
$var wire 8 v o_pc [7:0] $end
$var parameter 32 w DATA_WIDTH $end
$var reg 8 x register [7:0] $end
$upscope $end
$scope module pc_reg $end
$var wire 1 y i_bus_writable $end
$var wire 1 + i_clk $end
$var wire 1 , i_rst $end
$var wire 1 8 i_we $end
$var wire 8 z io_data [7:0] $end
$var wire 8 { o_pc [7:0] $end
$var parameter 32 | DATA_WIDTH $end
$var reg 8 } register [7:0] $end
$upscope $end
$scope module ram $end
$var wire 8 ~ i_addr [7:0] $end
$var wire 1 !" i_bus_writable $end
$var wire 1 + i_clk $end
$var wire 1 "" i_jmp_imme $end
$var wire 1 1 i_we $end
$var wire 8 #" io_data [7:0] $end
$var wire 8 $" out [7:0] $end
$var parameter 32 %" DATA_WIDTH $end
$var parameter 32 &" MEM_SIZE $end
$upscope $end
$scope module tmp $end
$var wire 1 '" i_bus_writable $end
$var wire 1 + i_clk $end
$var wire 1 , i_rst $end
$var wire 1 7 i_we $end
$var wire 8 (" io_data [7:0] $end
$var wire 8 )" o_pc [7:0] $end
$var parameter 32 *" DATA_WIDTH $end
$var reg 8 +" register [7:0] $end
$upscope $end
$upscope $end
$scope task print_ram $end
$var integer 32 ," i [31:0] $end
$upscope $end
$upscope $end
$enddefinitions $end
$comment Show the parameter values. $end
$dumpall
b1000 *"
b10000 &"
b1000 %"
b1000 |
b1000 w
b1000 r
b1000 n
b100000 f
b110 e
b0 d
b1 c
b1 b
b11 a
b10 `
b111 _
b101 ^
b110 ]
b100 \
b0 [
b100 Z
b100 Y
b1 X
b101 W
b111 V
b10 U
b11 T
b1000000 S
b10 R
b1000 Q
b1000 P
b10000 O
b1000 K
b1000 E
b1000 A
b1000 "
$end
#0
$dumpvars
bx ,"
b0 +"
b0 )"
b0 ("
0'"
b101111 $"
b0 #"
0""
0!"
b0 ~
b0 }
b0 {
b0 z
1y
b0 x
b0 v
b0 u
0t
b0 s
b0 q
b0 p
0o
b0 m
b0 l
0k
b0 j
0i
b1 h
b1 g
b0 N
b0 M
0L
b0 J
b0 I
0H
b0 G
b0 F
b0 D
b0 C
0B
b0 @
0?
0>
0=
0<
0;
0:
19
08
07
b0 6
b0 5
b0 4
b0 3
02
01
b1 0
b0 /
b0 .
bx -
1,
1+
b1010101010010110100111001010111 *
b10101000100110101010000 )
b101000001000011 (
b10011010100010101001101 '
b1001001010011100100001101010010 &
b1000011010101000101001001001100 %
b10000010100110001010101 $
b10000010100001101000011 #
b0 !
$end
#5
0+
#10
b101111 !
b101111 /
b101111 .
b101111 C
b101111 I
b101111 l
b101111 p
b101111 u
b101111 z
b101111 #"
b101111 ("
0y
1!"
b100 0
b10 g
1;
b100 h
09
b1 j
b1 -
1+
0,
#15
0+
#20
b101 g
19
0;
b10 j
b101111 @
b101111 N
b101111 q
b101111 s
b100 -
1+
#25
0+
#30
b100 !
b100 /
b100 .
b100 C
b100 I
b100 l
b100 p
b100 u
b100 z
b100 #"
b100 ("
b100 $"
b111 g
1=
09
b101111 5
b101111 v
b101111 x
b101111 ~
b101 j
1+
#35
0+
#40
b1 !
b1 /
b1 .
b1 C
b1 I
b1 l
b1 p
b1 u
b1 z
b1 #"
b1 ("
1k
0!"
b10 0
b0 g
18
b10 h
0=
b100 M
b111 j
b100 6
b100 D
b100 G
b100 F
1+
#45
0+
#50
1y
0k
b1 0
b1 !
b1 /
b1 .
b1 C
b1 I
b1 l
b1 p
b1 u
b1 z
b1 #"
b1 ("
b1 g
19
b1 h
08
b1 4
b1 m
b1 {
b1 }
b0 j
b10 -
1+
#55
0+
#60
b1110 !
b1110 /
b1110 .
b1110 C
b1110 I
b1110 l
b1110 p
b1110 u
b1110 z
b1110 #"
b1110 ("
0y
1!"
b100 0
b1110 $"
b10 g
1;
b100 h
09
b1 j
b1 5
b1 v
b1 x
b1 ~
b1 -
1+
#65
0+
#70
b100 g
19
0;
b1110 @
b1110 N
b1110 q
b1110 s
b10 j
b100 -
1+
#75
0+
#80
b1 !
b1 /
b1 .
b1 C
b1 I
b1 l
b1 p
b1 u
b1 z
b1 #"
b1 ("
b1 $"
b11 g
17
09
1i
b100 j
b1110 5
b1110 v
b1110 x
b1110 ~
1+
#85
0+
#90
b101 !
b101 /
b101 .
b101 C
b101 I
b101 l
b101 p
b101 u
b101 z
b101 #"
b101 ("
0!"
1H
b1000 0
b101 M
b111 g
1=
b1000 h
12
07
b1 3
b1 J
b1 )"
b1 +"
b11 j
1+
#95
0+
#100
1k
0H
b10 0
b10 !
b10 /
b10 .
b10 C
b10 I
b10 l
b10 p
b10 u
b10 z
b10 #"
b10 ("
b0 g
18
b10 h
0=
02
b100 M
b111 j
b101 6
b101 D
b101 G
b101 F
b1000 -
1+
#105
0+
#110
1y
0k
b1 0
b10 !
b10 /
b10 .
b10 C
b10 I
b10 l
b10 p
b10 u
b10 z
b10 #"
b10 ("
b1 g
19
b1 h
08
b10 4
b10 m
b10 {
b10 }
b0 j
b10 -
1+
#115
0+
#120
b111101 !
b111101 /
b111101 .
b111101 C
b111101 I
b111101 l
b111101 p
b111101 u
b111101 z
b111101 #"
b111101 ("
0y
1!"
b100 0
b111101 $"
b10 g
1;
b100 h
09
b1 j
b10 5
b10 v
b10 x
b10 ~
b1 -
1+
#125
0+
#130
b110 g
19
0;
b111101 @
b111101 N
b111101 q
b111101 s
b10 j
b100 -
1+
#135
0+
#140
0!"
1B
b101 !
b101 /
b101 .
b101 C
b101 I
b101 l
b101 p
b101 u
b101 z
b101 #"
b101 ("
b10000 0
b0 $"
b111 g
11
b10000 h
09
0i
b110 j
b111101 5
b111101 v
b111101 x
b111101 ~
1+
#145
0+
#150
b11 !
b11 /
b11 .
b11 C
b11 I
b11 l
b11 p
b11 u
b11 z
b11 #"
b11 ("
1k
0B
b10 0
b0 g
18
b10 h
01
b101 $"
b111 j
b10000 -
1+
#155
0+
#160
1y
0k
b1 0
b1 g
19
b1 h
08
b11 !
b11 /
b11 .
b11 C
b11 I
b11 l
b11 p
b11 u
b11 z
b11 #"
b11 ("
b0 j
b11 4
b11 m
b11 {
b11 }
b10 -
1+
#165
0+
#170
b11110 !
b11110 /
b11110 .
b11110 C
b11110 I
b11110 l
b11110 p
b11110 u
b11110 z
b11110 #"
b11110 ("
0y
1!"
b11110 $"
b100 0
b10 g
1;
b100 h
09
b11 5
b11 v
b11 x
b11 ~
b1 j
b1 -
1+
#175
0+
#180
b100 g
19
0;
b10 j
b11110 @
b11110 N
b11110 q
b11110 s
b100 -
1+
#185
0+
#190
b1 !
b1 /
b1 .
b1 C
b1 I
b1 l
b1 p
b1 u
b1 z
b1 #"
b1 ("
b1 $"
b11 g
17
09
b11110 5
b11110 v
b11110 x
b11110 ~
b100 j
1+
#195
0+
#200
b100 !
b100 /
b100 .
b100 C
b100 I
b100 l
b100 p
b100 u
b100 z
b100 #"
b100 ("
0!"
1H
b1000 0
b111 g
1=
b1000 h
07
b11 j
1+
#205
0+
#210
1k
0H
b100 !
b100 /
b100 .
b100 C
b100 I
b100 l
b100 p
b100 u
b100 z
b100 #"
b100 ("
b10 0
b11 M
b0 g
18
b10 h
0=
b100 6
b100 D
b100 G
b100 F
b111 j
b1000 -
1+
#215
0+
#220
1y
0k
b1 0
b1 g
19
b1 h
08
b100 !
b100 /
b100 .
b100 C
b100 I
b100 l
b100 p
b100 u
b100 z
b100 #"
b100 ("
b0 j
b100 4
b100 m
b100 {
b100 }
b10 -
1+
#225
0+
#230
b101101 !
b101101 /
b101101 .
b101101 C
b101101 I
b101101 l
b101101 p
b101101 u
b101101 z
b101101 #"
b101101 ("
0y
1!"
b101101 $"
b100 0
b10 g
1;
b100 h
09
b100 5
b100 v
b100 x
b100 ~
b1 j
b1 -
1+
#235
0+
#240
b101 g
19
0;
b10 j
b101101 @
b101101 N
b101101 q
b101101 s
b100 -
1+
#245
0+
